Augusta/Augusta.py
Augusta/RNASeq_normalization.py
Augusta/SBML_generation.py
Augusta/__init__.py
Augusta/core.py
Augusta/data_export.py
Augusta/data_import.py
Augusta/motif_discovery.py
Augusta/DBs/CC_search_filter.py
Augusta/DBs/DBs_filter.py
Augusta/DBs/DBs_search.py
Augusta/DBs/__init__.py
Augusta/DBs/get_synonyms.py
Augusta/GRN_MI/GRNmi_infer.py
Augusta/GRN_MI/__init__.py
Augusta/GRN_MI/preprocessing.py
Augusta/cno/__init__.py
Augusta/cno/io/__init__.py
Augusta/cno/io/adj2sif.py
Augusta/cno/io/cna.py
Augusta/cno/io/cnograph.py
Augusta/cno/io/eda.py
Augusta/cno/io/mapback.py
Augusta/cno/io/measurements.py
Augusta/cno/io/metabolites.py
Augusta/cno/io/midas.py
Augusta/cno/io/midas_normalisation.py
Augusta/cno/io/multigraph.py
Augusta/cno/io/multimidas.py
Augusta/cno/io/net.py
Augusta/cno/io/obs.py
Augusta/cno/io/randomisation.py
Augusta/cno/io/reactions.py
Augusta/cno/io/sbml.py
Augusta/cno/io/sbmlqual.py
Augusta/cno/io/sif.py
Augusta/cno/io/sif2asp.py
Augusta/cno/io/sop2sif.py
Augusta/cno/io/validation.py
Augusta/cno/io/xcnograph.py
Augusta/cno/io/xmlmidas.py
Augusta/cno/misc/__init__.py
Augusta/cno/misc/classifier.py
Augusta/cno/misc/dependencies.py
Augusta/cno/misc/matfun.py
Augusta/cno/misc/profiler.py
Augusta/cno/misc/tools.py
Augusta/cno/misc/truthtable.py
augusta-1.0.7.dist-info/licenses/LICENSE
augusta-1.0.7.dist-info/METADATA
augusta-1.0.7.dist-info/WHEEL
augusta-1.0.7.dist-info/top_level.txt
augusta-1.0.7.dist-info/RECORD
