Metadata-Version: 2.4
Name: Augusta
Version: 1.0.7
Summary: Python package for inference of the gene regulatory network and the boolean network using RNA-Seq data.
Home-page: https://github.com/JanaMus/Augusta
Author: Jana Musilova, Zdenek Vafek, Karel Sedlar
Author-email: musilovajana@vut.cz
License: MIT
Keywords: Computational biology,Bioinformatics,RNA-Seq,mutual information,database,Boolean network,Gene Regulatory network,SBML
Classifier: Programming Language :: Python :: 3
Classifier: License :: OSI Approved :: MIT License
Classifier: Operating System :: OS Independent
Classifier: Development Status :: 4 - Beta
Requires-Python: >=3.7, <3.9
License-File: LICENSE
Requires-Dist: pandas
Requires-Dist: numpy
Requires-Dist: scikit-learn
Requires-Dist: bioinfokit
Requires-Dist: Bio<=1.79
Requires-Dist: docker
Requires-Dist: EcoNameTranslator
Requires-Dist: mygene
Requires-Dist: omnipath<1.0.8
Requires-Dist: urllib3>=1.26.0
Requires-Dist: requests>=2.24.0
Requires-Dist: bs4
Requires-Dist: lxml
Requires-Dist: html5lib
Requires-Dist: networkx==1.11
Requires-Dist: easydev
Requires-Dist: colormap
Requires-Dist: ccapi==0.1.0
Dynamic: author
Dynamic: author-email
Dynamic: classifier
Dynamic: description
Dynamic: home-page
Dynamic: keywords
Dynamic: license
Dynamic: license-file
Dynamic: requires-dist
Dynamic: requires-python
Dynamic: summary
